LICENSE
MANIFEST.in
Makefile
README.rst
setup.py
bunga/__init__.py
bunga/__main__.py
bunga/bunga_client.py
bunga/bunga_pb2.py
bunga/client.py
bunga/linux.py
bunga/version.py
bunga.egg-info/PKG-INFO
bunga.egg-info/SOURCES.txt
bunga.egg-info/dependency_links.txt
bunga.egg-info/entry_points.txt
bunga.egg-info/requires.txt
bunga.egg-info/top_level.txt
bunga/subparsers/__init__.py
bunga/subparsers/execute.py
bunga/subparsers/get_file.py
bunga/subparsers/log.py
bunga/subparsers/plot.py
bunga/subparsers/put_file.py
bunga/subparsers/shell.py
proto/bunga.proto
tests/__init__.py
tests/test_client.py
tests/test_command_line.py
tests/test_linux.py
tests/test_shell.py
tests/utils.py