Metadata-Version: 1.1
Name: bunga
Version: 0.45.0
Summary: Control and monitor your system.
Home-page: https://github.com/eerimoq/bunga
Author: Erik Moqvist
Author-email: erik.moqvist@gmail.com
License: MIT
Platform: UNKNOWN
Classifier: License :: OSI Approved :: MIT License
Classifier: Programming Language :: Python :: 3
